src/__init__.py
mseep_mseep_metabase_mcp-0.1.0.dist-info/METADATA
mseep_mseep_metabase_mcp-0.1.0.dist-info/WHEEL
mseep_mseep_metabase_mcp-0.1.0.dist-info/top_level.txt
mseep_mseep_metabase_mcp-0.1.0.dist-info/RECORD
