Metadata-Version: 2.4
Name: mseep_mseep-metabase-mcp
Version: 0.1.0
Summary: Package published under mseep brand
Author-email: mseep <support@skydeck.ai>
Requires-Python: >=3.8
Dynamic: requires-python
